[
  {
    "artist": "CHRISTINA STUERMER",
    "title": "ICH LEBE",
    "count": 1
  },
  {
    "artist": "FLEETWOOD MAC",
    "title": "LITTLE LIES",
    "count": 1
  },
  {
    "artist": "SLADE",
    "title": "MY OH MY",
    "count": 1
  },
  {
    "artist": "ALL-4-ONE",
    "title": "I SWEAR",
    "count": 1
  },
  {
    "artist": "ELTON JOHN",
    "title": "I GUESS THAT&#39;S WHY THEY CALL IT THE BLUES",
    "count": 1
  },
  {
    "artist": "LP",
    "title": "LOST ON YOU",
    "count": 1
  },
  {
    "artist": "CAT STEVENS",
    "title": "LADY D&#39;ARBANVILLE",
    "count": 1
  },
  {
    "artist": "REVOLVERHELD",
    "title": "LASS UNS GEHEN",
    "count": 1
  },
  {
    "artist": "HERBERT GROENEMEYER",
    "title": "MUSIK NUR, WENN SIE LAUT IST",
    "count": 1
  },
  {
    "artist": "JOACHIM WITT",
    "title": "GOLDENER REITER",
    "count": 1
  },
  {
    "artist": "GARETH GATES",
    "title": "ANYONE OF US (STUPID MISTAKE)",
    "count": 1
  },
  {
    "artist": "TOMMY ROE",
    "title": "SHEILA",
    "count": 1
  },
  {
    "artist": "ROBIN SCHULZ &amp; DAVID feat. CHEAT CODES GUETTA",
    "title": "SHED A LIGHT",
    "count": 1
  },
  {
    "artist": "BEE GEES",
    "title": "YOU WIN AGAIN",
    "count": 1
  },
  {
    "artist": "CHICAGO",
    "title": "HARD TO SAY I&#39;M SORRY",
    "count": 1
  },
  {
    "artist": "ROXETTE",
    "title": "FADING LIKE A FLOWER (EVERY TIME YOU LEAVE)",
    "count": 1
  },
  {
    "artist": "MICHAEL JACKSON",
    "title": "BEAT IT",
    "count": 1
  },
  {
    "artist": "ACE OF BASE",
    "title": "ALWAYS HAVE, ALWAYS WILL",
    "count": 1
  },
  {
    "artist": "ECHOSMITH",
    "title": "COOL KIDS",
    "count": 2
  },
  {
    "artist": "ALBERT HAMMOND",
    "title": "DOWN BY THE RIVER",
    "count": 1
  },
  {
    "artist": "REA GARVEY",
    "title": "WILD LOVE",
    "count": 1
  },
  {
    "artist": "FATS DOMINO",
    "title": "I&#39;M WALKING",
    "count": 1
  },
  {
    "artist": "EAGLES",
    "title": "HOTEL CALIFORNIA (SHORT)",
    "count": 1
  },
  {
    "artist": "BEATLES",
    "title": "HELLO GOODBYE",
    "count": 1
  },
  {
    "artist": "PUHDYS",
    "title": "ALT WIE EIN BAUM",
    "count": 2
  },
  {
    "artist": "FEARGAL SHARKEY",
    "title": "A GOOD HEART",
    "count": 1
  },
  {
    "artist": "BELOVED",
    "title": "SWEET HARMONY",
    "count": 2
  },
  {
    "artist": "DIRE STRAITS",
    "title": "WALK OF LIFE",
    "count": 1
  },
  {
    "artist": "HOT CHOCOLATE",
    "title": "EVERY 1&#39;S A WINNER",
    "count": 1
  },
  {
    "artist": "OTTAWAN",
    "title": "D.I.S.C.O. (DISCO)",
    "count": 1
  },
  {
    "artist": "ERIC CARMEN",
    "title": "ALL BY MYSELF",
    "count": 1
  },
  {
    "artist": "ANDREAS BOURANI",
    "title": "HEY",
    "count": 1
  },
  {
    "artist": "JERMAINE JACKSON &amp; PIA ZADORA",
    "title": "WHEN THE RAIN BEGINS TO FALL",
    "count": 1
  },
  {
    "artist": "SUNRISE AVENUE",
    "title": "NOTHING IS OVER",
    "count": 1
  },
  {
    "artist": "DONNA SUMMER",
    "title": "SHE WORKS HARD FOR THE MONEY",
    "count": 1
  },
  {
    "artist": "ANDRU DONALDS",
    "title": "ALL OUT OF LOVE",
    "count": 1
  },
  {
    "artist": "JASON DONOVAN",
    "title": "RHYTHM OF THE RAIN",
    "count": 1
  },
  {
    "artist": "BAP",
    "title": "ALLES EM LOT",
    "count": 1
  },
  {
    "artist": "OMI",
    "title": "CHEERLEADER",
    "count": 1
  },
  {
    "artist": "LIONEL RICHIE",
    "title": "JUST FOR YOU",
    "count": 1
  },
  {
    "artist": "CHRIS DE BURGH",
    "title": "DON&#39;T PAY THE FERRYMAN",
    "count": 1
  },
  {
    "artist": "RICHARD MARX",
    "title": "RIGHT HERE WAITING",
    "count": 1
  },
  {
    "artist": "UDO LINDENBERG",
    "title": "CLUB DER MILLIONAERE",
    "count": 1
  },
  {
    "artist": "KELLY CLARKSON",
    "title": "HEARTBEAT SONG",
    "count": 1
  },
  {
    "artist": "SHAKIRA FEAT. FRESHLYGROUND",
    "title": "WAKA WAKA (THIS TIME FOR AFRICA)",
    "count": 1
  },
  {
    "artist": "FOSTER THE PEOPLE",
    "title": "PUMPED UP KICKS",
    "count": 1
  },
  {
    "artist": "MIKE &amp; THE MECHANICS",
    "title": "SILENT RUNNING",
    "count": 1
  },
  {
    "artist": "ACHIM REICHEL",
    "title": "ALOHA HEJA HE",
    "count": 1
  },
  {
    "artist": "ROLLING STONES",
    "title": "START ME UP",
    "count": 1
  },
  {
    "artist": "ROBBIE WILLIAMS",
    "title": "LOVE MY LIFE",
    "count": 2
  },
  {
    "artist": "SARAH CONNOR",
    "title": "BEDINGUNGSLOS",
    "count": 1
  },
  {
    "artist": "JOHANNES OERDING",
    "title": "ALLES BRENNT",
    "count": 2
  },
  {
    "artist": "VILLE VALO &amp; NATALIA AVELON",
    "title": "SUMMER WINE",
    "count": 1
  },
  {
    "artist": "AMY MACDONALD",
    "title": "MR ROCK &amp; ROLL",
    "count": 1
  },
  {
    "artist": "BILL MEDLEY &amp; JENNIFER WARNES",
    "title": "(I&#39;VE HAD) THE TIME OF MY LIFE",
    "count": 1
  },
  {
    "artist": "LADY GAGA",
    "title": "BAD ROMANCE",
    "count": 1
  },
  {
    "artist": "PRINZEN",
    "title": "ALLES NUR GEKLAUT",
    "count": 1
  },
  {
    "artist": "JUSTIN BIEBER",
    "title": "LOVE YOURSELF",
    "count": 2
  },
  {
    "artist": "MEN AT WORK",
    "title": "DOWN UNDER",
    "count": 1
  },
  {
    "artist": "INNER CIRCLE",
    "title": "ROCK WITH YOU",
    "count": 1
  },
  {
    "artist": "C. C. CATCH",
    "title": "I CAN LOSE MY HEART TONIGHT",
    "count": 1
  },
  {
    "artist": "MARIA MENA",
    "title": "ALL THIS TIME (PICK-ME-UP SONG)",
    "count": 1
  },
  {
    "artist": "LINDA RONSTADT",
    "title": "IT&#39;S SO EASY",
    "count": 1
  },
  {
    "artist": "MADONNA",
    "title": "THE POWER OF GOODBYE",
    "count": 1
  },
  {
    "artist": "GIBSON BROTHERS",
    "title": "QUE SERA MI VIDA",
    "count": 1
  },
  {
    "artist": "GERRY RAFFERTY",
    "title": "BAKER STREET",
    "count": 1
  },
  {
    "artist": "PASO DOBLE",
    "title": "COMPUTERLIEBE",
    "count": 1
  },
  {
    "artist": "NO MERCY",
    "title": "WHERE DO YOU GO",
    "count": 1
  },
  {
    "artist": "BUGGLES",
    "title": "VIDEO KILLED THE RADIO STAR",
    "count": 1
  },
  {
    "artist": "SHAWN MENDES",
    "title": "TREAT YOU BETTER",
    "count": 2
  },
  {
    "artist": "ICH + ICH",
    "title": "STARK",
    "count": 1
  },
  {
    "artist": "SHEILA &amp; B. DEVOTION",
    "title": "SPACER",
    "count": 1
  },
  {
    "artist": "AXEL PRAHL",
    "title": "WANN, SAG WANN",
    "count": 1
  },
  {
    "artist": "PET SHOP BOYS",
    "title": "DOMINO DANCING",
    "count": 1
  },
  {
    "artist": "FOREIGNER",
    "title": "I DON&#39;T WANT TO LIVE WITHOUT YOU",
    "count": 1
  },
  {
    "artist": "HOT CHOCOLATE",
    "title": "YOU SEXY THING",
    "count": 1
  },
  {
    "artist": "STANFOUR",
    "title": "WISHING YOU WELL",
    "count": 2
  },
  {
    "artist": "NELLY FURTADO",
    "title": "SAY IT RIGHT",
    "count": 1
  },
  {
    "artist": "ELTON JOHN",
    "title": "DON&#39;T GO BREAKING MY HEART",
    "count": 1
  },
  {
    "artist": "NEIL DIAMOND",
    "title": "BEAUTIFUL NOISE",
    "count": 1
  },
  {
    "artist": "MADS LANGER",
    "title": "YOU&#39;RE NOT ALONE",
    "count": 1
  },
  {
    "artist": "MIKE POSNER",
    "title": "I TOOK A PILL IN IBIZA",
    "count": 1
  },
  {
    "artist": "ED SHEERAN",
    "title": "PHOTOGRAPH",
    "count": 1
  },
  {
    "artist": "DES&#39;REE",
    "title": "LIFE",
    "count": 1
  },
  {
    "artist": "ROBERT MILES",
    "title": "CHILDREN",
    "count": 1
  },
  {
    "artist": "YEARS &amp; YEARS",
    "title": "KING",
    "count": 1
  },
  {
    "artist": "A-HA",
    "title": "THE SUN ALWAYS SHINES ON TV",
    "count": 2
  },
  {
    "artist": "WESTERNHAGEN",
    "title": "WIEDER HIER",
    "count": 1
  },
  {
    "artist": "NORMAN GREENBAUM",
    "title": "SPIRIT IN THE SKY",
    "count": 1
  },
  {
    "artist": "TINA TURNER",
    "title": "THE BEST",
    "count": 1
  },
  {
    "artist": "RED GARLAND QUINTET",
    "title": "LOVE IS HERE TO STAY",
    "count": 1
  },
  {
    "artist": "TREMELOES",
    "title": "SILENCE IS GOLDEN",
    "count": 1
  },
  {
    "artist": "MIKE &amp; THE MECHANICS",
    "title": "EVERYBODY GETS A SECOND CHANCE",
    "count": 1
  },
  {
    "artist": "DIE AERZTE",
    "title": "LASSE REDN",
    "count": 1
  },
  {
    "artist": "TALKING HEADS",
    "title": "ROAD TO NOWHERE",
    "count": 1
  },
  {
    "artist": "FANCY",
    "title": "SLICE ME NICE",
    "count": 1
  },
  {
    "artist": "JOE COCKER",
    "title": "N&#39;OUBLIEZ JAMAIS",
    "count": 1
  },
  {
    "artist": "MILOW",
    "title": "HOWLING AT THE MOON",
    "count": 1
  },
  {
    "artist": "MICHAEL BUBL&Eacute;",
    "title": "IT&#39;S A BEAUTIFUL DAY",
    "count": 1
  },
  {
    "artist": "PAT BENATAR",
    "title": "WE BELONG",
    "count": 1
  },
  {
    "artist": "STEFAN GWILDIS",
    "title": "SIE",
    "count": 1
  },
  {
    "artist": "PET SHOP BOYS",
    "title": "WEST END GIRLS",
    "count": 1
  },
  {
    "artist": "BENNY GOODMAN SEXTET &amp; CHARLIE CHRISTIAN",
    "title": "CHARLIE&#39;S DREAM (ALBUM VERSION)",
    "count": 1
  },
  {
    "artist": "OLIVER ONIONS",
    "title": "FLYING THROUGH THE AIR",
    "count": 1
  },
  {
    "artist": "CYNDI LAUPER",
    "title": "TRUE COLORS",
    "count": 1
  },
  {
    "artist": "KINCADE",
    "title": "DREAMS ARE TEN A PENNY",
    "count": 1
  },
  {
    "artist": "AMY GRANT",
    "title": "BABY BABY",
    "count": 1
  },
  {
    "artist": "LAID BACK",
    "title": "BAKERMAN",
    "count": 1
  },
  {
    "artist": "ANDREAS BOURANI",
    "title": "AUF UNS",
    "count": 1
  },
  {
    "artist": "JOHNNY HATES JAZZ",
    "title": "TURN BACK THE CLOCK",
    "count": 1
  },
  {
    "artist": "LIONEL RICHIE",
    "title": "ANGEL",
    "count": 1
  },
  {
    "artist": "ELLIE GOULDING",
    "title": "LIGHTS",
    "count": 1
  },
  {
    "artist": "LEONA LEWIS",
    "title": "BLEEDING LOVE",
    "count": 1
  },
  {
    "artist": "ROY ORBISON",
    "title": "PRETTY WOMAN",
    "count": 1
  },
  {
    "artist": "JONAH",
    "title": "ALL WE ARE",
    "count": 1
  },
  {
    "artist": "BILLY RAY CYRUS",
    "title": "ACHY BREAKY HEART",
    "count": 1
  },
  {
    "artist": "MADONNA",
    "title": "MILES AWAY",
    "count": 1
  },
  {
    "artist": "MARSHALL &amp; HAIN",
    "title": "DANCING IN THE CITY",
    "count": 1
  },
  {
    "artist": "NATASHA THOMAS",
    "title": "IT&#39;S OVER NOW",
    "count": 1
  },
  {
    "artist": "EURYTHMICS",
    "title": "HERE COMES THE RAIN AGAIN",
    "count": 1
  },
  {
    "artist": "NANCY SINATRA",
    "title": "THESE BOOTS ARE MADE FOR WALKIN&#39;",
    "count": 2
  },
  {
    "artist": "MARIANNE FAITHFULL",
    "title": "THE BALLAD OF LUCY JORDAN",
    "count": 1
  },
  {
    "artist": "KOOL &amp; THE GANG",
    "title": "CHERISH",
    "count": 1
  },
  {
    "artist": "SASHA",
    "title": "WE CAN LEAVE THE WORLD",
    "count": 1
  },
  {
    "artist": "NENA",
    "title": "? (FRAGEZEICHEN)",
    "count": 1
  },
  {
    "artist": "LUMINEERS",
    "title": "HO HEY",
    "count": 1
  },
  {
    "artist": "FRANS",
    "title": "IF I WERE SORRY",
    "count": 1
  },
  {
    "artist": "PETER MAFFAY",
    "title": "SONNE IN DER NACHT",
    "count": 1
  },
  {
    "artist": "ELLIE GOULDING",
    "title": "SOMETHING IN THE WAY YOU MOVE",
    "count": 1
  },
  {
    "artist": "WHITNEY HOUSTON",
    "title": "I WANNA DANCE WITH SOMEBODY",
    "count": 1
  },
  {
    "artist": "ROD STEWART",
    "title": "RHYTHM OF MY HEART",
    "count": 1
  },
  {
    "artist": "AVICII VS. CONRAD SEWELL",
    "title": "TASTE THE FEELING",
    "count": 2
  },
  {
    "artist": "BLOODHOUND GANG",
    "title": "THE BAD TOUCH",
    "count": 1
  },
  {
    "artist": "PETER MAFFAY",
    "title": "HALT DICH AN MIR FEST",
    "count": 1
  },
  {
    "artist": "KISS",
    "title": "I WAS MADE FOR LOVIN&#39; YOU",
    "count": 1
  },
  {
    "artist": "BRUCE SPRINGSTEEN",
    "title": "HUNGRY HEART",
    "count": 1
  },
  {
    "artist": "EMPIRE OF THE SUN",
    "title": "WE ARE THE PEOPLE",
    "count": 1
  },
  {
    "artist": "JUSTIN TIMBERLAKE",
    "title": "CAN&#39;T STOP THE FEELING!",
    "count": 1
  },
  {
    "artist": "DIANA ROSS",
    "title": "CHAIN REACTION",
    "count": 1
  },
  {
    "artist": "VANGELIS",
    "title": "CONQUEST OF PARADISE",
    "count": 1
  },
  {
    "artist": "STEVE MILLER BAND",
    "title": "ABRACADABRA",
    "count": 1
  },
  {
    "artist": "ELECTRIC LIGHT ORCHESTRA",
    "title": "HOLD ON TIGHT",
    "count": 1
  },
  {
    "artist": "FLEETWOOD MAC",
    "title": "GO YOUR OWN WAY",
    "count": 1
  },
  {
    "artist": "NENA",
    "title": "NUR GETRAEUMT",
    "count": 1
  },
  {
    "artist": "SANTA ESMERALDA",
    "title": "DON&#39;T LET ME BE MISUNDERSTOOD",
    "count": 1
  },
  {
    "artist": "ANIMALS",
    "title": "THE HOUSE OF THE RISING SUN",
    "count": 1
  },
  {
    "artist": "ERIC CARMEN",
    "title": "HUNGRY EYES",
    "count": 1
  },
  {
    "artist": "CHARLES &amp; EDDIE",
    "title": "WOULD I LIE TO YOU?",
    "count": 1
  },
  {
    "artist": "ZUCCHERO",
    "title": "DIAMANTE",
    "count": 1
  },
  {
    "artist": "FIFTH HARMONY",
    "title": "WORK FROM HOME",
    "count": 1
  },
  {
    "artist": "ZARA LARSSON",
    "title": "LUSH LIFE",
    "count": 1
  },
  {
    "artist": "KLAUS LAGE",
    "title": "MONOPOLI",
    "count": 1
  },
  {
    "artist": "ALANIS MORISSETTE",
    "title": "IRONIC",
    "count": 1
  },
  {
    "artist": "ROD STEWART",
    "title": "EVERY BEAT OF MY HEART",
    "count": 1
  },
  {
    "artist": "K&#39;NAAN",
    "title": "WAVIN&#39;  FLAG (CELEBRATION MIX)",
    "count": 1
  },
  {
    "artist": "CHICAGO",
    "title": "YOU&#39;RE THE INSPIRATION",
    "count": 1
  },
  {
    "artist": "ELLE KING",
    "title": "EX&#39;S &amp; OH&#39;S",
    "count": 1
  },
  {
    "artist": "RUBETTES",
    "title": "TONIGHT",
    "count": 1
  },
  {
    "artist": "LAITH AL-DEEN",
    "title": "DEIN LIED",
    "count": 1
  },
  {
    "artist": "TONY BENNETT &amp; K.D. LANG",
    "title": "MOONGLOW",
    "count": 1
  },
  {
    "artist": "BELINDA CARLISLE",
    "title": "CIRCLE IN THE SAND",
    "count": 1
  },
  {
    "artist": "CASSANDRA STEEN &amp; ADEL TAWIL",
    "title": "STADT",
    "count": 1
  },
  {
    "artist": "VAN  HALEN",
    "title": "JUMP",
    "count": 1
  },
  {
    "artist": "ADELE",
    "title": "SEND MY LOVE (TO YOUR NEW LOVER)",
    "count": 2
  },
  {
    "artist": "BRUCE SPRINGSTEEN",
    "title": "I&#39;M ON FIRE",
    "count": 1
  },
  {
    "artist": "DIANA ROSS",
    "title": "I CAN&#39;T GET STARTED",
    "count": 1
  },
  {
    "artist": "JANET JACKSON",
    "title": "WHOOPS NOW",
    "count": 1
  },
  {
    "artist": "CLIFF RICHARD",
    "title": "POWER TO ALL OUR FRIENDS",
    "count": 1
  },
  {
    "artist": "WESTERNHAGEN",
    "title": "WILLENLOS",
    "count": 2
  },
  {
    "artist": "HELLO",
    "title": "NEW YORK GROOVE",
    "count": 1
  },
  {
    "artist": "JOHNNY WAKELIN",
    "title": "IN ZAIRE",
    "count": 1
  },
  {
    "artist": "HOLLIES",
    "title": "BUS STOP",
    "count": 1
  },
  {
    "artist": "DEICHKIND",
    "title": "LUFTBAHN",
    "count": 1
  },
  {
    "artist": "BAY CITY ROLLERS",
    "title": "BYE BYE BABY",
    "count": 1
  },
  {
    "artist": "BEACH BOYS",
    "title": "BARBARA ANN",
    "count": 1
  },
  {
    "artist": "AMY MACDONALD",
    "title": "THIS IS THE LIFE",
    "count": 1
  },
  {
    "artist": "MIDDLE OF THE ROAD",
    "title": "SACRAMENTO",
    "count": 1
  },
  {
    "artist": "2RAUMWOHNUNG",
    "title": "BESSER GEHT&#39;S NICHT",
    "count": 2
  },
  {
    "artist": "CHER",
    "title": "BELIEVE",
    "count": 1
  },
  {
    "artist": "POINTER SISTERS",
    "title": "SLOW HAND",
    "count": 1
  },
  {
    "artist": "CREEDENCE CLEARWATER REVIVAL",
    "title": "LOOKIN&#39; OUT MY BACK DOOR",
    "count": 1
  },
  {
    "artist": "GREEN DAY",
    "title": "BOULEVARD OF BROKEN DREAMS",
    "count": 1
  },
  {
    "artist": "LA BIONDA",
    "title": "ONE FOR YOU, ONE FOR ME",
    "count": 1
  },
  {
    "artist": "MARK FORSTER",
    "title": "BAUCH UND KOPF",
    "count": 1
  },
  {
    "artist": "CREEDENCE CLEARWATER REVIVAL",
    "title": "WHO&#39;LL STOP THE RAIN",
    "count": 1
  },
  {
    "artist": "DOORS",
    "title": "RIDERS ON THE STORM",
    "count": 1
  },
  {
    "artist": "M-PEOPLE",
    "title": "MOVING ON UP",
    "count": 1
  },
  {
    "artist": "VANESSA AMOROSI",
    "title": "ABSOLUTELY EVERYBODY",
    "count": 1
  },
  {
    "artist": "SIA",
    "title": "CHEAP THRILLS",
    "count": 1
  },
  {
    "artist": "ABBA",
    "title": "SUPER TROUPER",
    "count": 1
  },
  {
    "artist": "ADEL TAWIL",
    "title": "UNSERE LIEDER",
    "count": 1
  },
  {
    "artist": "CELINE DION",
    "title": "I&#39;M ALIVE",
    "count": 1
  },
  {
    "artist": "FOOLS GARDEN",
    "title": "LEMON TREE",
    "count": 1
  },
  {
    "artist": "LONDONBEAT",
    "title": "I&#39;VE BEEN THINKING ABOUT YOU",
    "count": 1
  },
  {
    "artist": "FALCO",
    "title": "DER KOMMISSAR",
    "count": 1
  },
  {
    "artist": "BLIND DATE",
    "title": "YOUR HEART KEEPS BURNING",
    "count": 1
  },
  {
    "artist": "SPENCER DAVIS GROUP",
    "title": "KEEP ON RUNNING",
    "count": 1
  },
  {
    "artist": "CHRIS REA",
    "title": "FOOL (IF YOU THINK IT&#39;S OVER)",
    "count": 1
  },
  {
    "artist": "A-HA",
    "title": "FOOT OF THE MOUNTAIN",
    "count": 1
  },
  {
    "artist": "HERBERT GROENEMEYER",
    "title": "LIED 1EIN STUECK VOM HIMMEL",
    "count": 1
  },
  {
    "artist": "NIK KERSHAW",
    "title": "WOULDN&#39;T IT BE GOOD",
    "count": 1
  },
  {
    "artist": "ALESSIA CARA",
    "title": "SCARS TO YOUR BEAUTIFUL",
    "count": 1
  },
  {
    "artist": "SILBERMOND",
    "title": "B 96",
    "count": 1
  },
  {
    "artist": "DIE AERZTE",
    "title": "MAENNER SIND SCHWEINE",
    "count": 1
  },
  {
    "artist": "CLIFF RICHARD",
    "title": "DREAMIN&#39;",
    "count": 1
  },
  {
    "artist": "VILLAGE PEOPLE",
    "title": "IN THE NAVY",
    "count": 1
  },
  {
    "artist": "PRINCE ITAL JOE FEAT. MARKY MARK",
    "title": "UNITED",
    "count": 1
  },
  {
    "artist": "LAITH AL-DEEN",
    "title": "BILDER VON DIR",
    "count": 1
  },
  {
    "artist": "JUPITER JONES",
    "title": "STILL",
    "count": 1
  },
  {
    "artist": "BILLY OCEAN",
    "title": "LOVE REALLY HURTS WITHOUT YOU",
    "count": 1
  },
  {
    "artist": "MATHOU",
    "title": "YOU NEVER WALK ALONE",
    "count": 1
  },
  {
    "artist": "ROBBIE WILLIAMS",
    "title": "FEEL",
    "count": 1
  },
  {
    "artist": "ROLLING STONES",
    "title": "PAINT IT BLACK",
    "count": 1
  },
  {
    "artist": "ROD STEWART",
    "title": "DA YA THINK I&#39;M SEXY",
    "count": 1
  },
  {
    "artist": "ALVARO SOLER",
    "title": "SOFIA",
    "count": 1
  },
  {
    "artist": "WINCENT WEISS",
    "title": "MUSIK SEIN",
    "count": 2
  },
  {
    "artist": "TONY CAREY",
    "title": "ROOM WITH A VIEW",
    "count": 1
  },
  {
    "artist": "ELTON JOHN",
    "title": "NIKITA",
    "count": 1
  },
  {
    "artist": "SANTIANO",
    "title": "LIEDER DER FREIHEIT",
    "count": 1
  },
  {
    "artist": "JENNIFER RUSH",
    "title": "DESTINY",
    "count": 1
  },
  {
    "artist": "CHRISTIE",
    "title": "YELLOW RIVER",
    "count": 1
  },
  {
    "artist": "COLESKE",
    "title": "TAKE ME WHERE THE SUN IS SHINING",
    "count": 1
  },
  {
    "artist": "MENTAL AS ANYTHING",
    "title": "LIVE IT UP",
    "count": 1
  },
  {
    "artist": "LADY GAGA",
    "title": "POKER FACE",
    "count": 1
  },
  {
    "artist": "MADONNA",
    "title": "HUNG UP",
    "count": 1
  },
  {
    "artist": "FELIX FEAT. POLINA JAEHN",
    "title": "BOOK OF LOVE",
    "count": 1
  },
  {
    "artist": "BELINDA CARLISLE",
    "title": "LEAVE A LIGHT ON",
    "count": 1
  },
  {
    "artist": "WES",
    "title": "ALANE",
    "count": 1
  },
  {
    "artist": "ADELE",
    "title": "WATER UNDER THE BRIDGE",
    "count": 1
  },
  {
    "artist": "KENNY ROGERS",
    "title": "LUCILLE",
    "count": 1
  },
  {
    "artist": "MANFRED MANN",
    "title": "DO WAH DIDDY DIDDY",
    "count": 1
  },
  {
    "artist": "LIONEL RICHIE",
    "title": "SAY YOU, SAY ME",
    "count": 1
  },
  {
    "artist": "NENA",
    "title": "99 LUFTBALLONS",
    "count": 4
  },
  {
    "artist": "BEATLES",
    "title": "A HARD DAY&#39;S NIGHT",
    "count": 1
  },
  {
    "artist": "AMERICAN AUTHORS",
    "title": "BEST DAY OF MY LIFE",
    "count": 2
  },
  {
    "artist": "DIZZY GILLESPIE",
    "title": "KING PORTER STOMP",
    "count": 1
  },
  {
    "artist": "ABBA",
    "title": "HONEY, HONEY",
    "count": 1
  },
  {
    "artist": "ALAN WALKER",
    "title": "SING ME TO SLEEP",
    "count": 2
  },
  {
    "artist": "PET SHOP BOYS",
    "title": "IT&#39;S A SIN",
    "count": 1
  },
  {
    "artist": "CARLY RAE JEPSEN",
    "title": "I REALLY LIKE YOU",
    "count": 1
  },
  {
    "artist": "TAYLOR SWIFT",
    "title": "BLANK SPACE",
    "count": 1
  },
  {
    "artist": "JAMES TAYLOR",
    "title": "YOU&#39;VE GOT A FRIEND",
    "count": 1
  },
  {
    "artist": "ROD STEWART",
    "title": "YOUNG TURKS",
    "count": 1
  },
  {
    "artist": "THE CLARKE-BOLAND BIG BAND",
    "title": "UM GRAO DE AREIA",
    "count": 1
  },
  {
    "artist": "BANGLES",
    "title": "ETERNAL FLAME",
    "count": 1
  },
  {
    "artist": "MIKE OLDFIELD &amp; MAGGIE REILLY",
    "title": "MOONLIGHT SHADOW",
    "count": 1
  },
  {
    "artist": "ZUCCHERO",
    "title": "IL VOLO",
    "count": 1
  },
  {
    "artist": "ONE DIRECTION",
    "title": "STORY OF MY LIFE",
    "count": 1
  },
  {
    "artist": "BELLINI",
    "title": "SAMBA DE JANEIRO",
    "count": 1
  },
  {
    "artist": "BEACH BOYS",
    "title": "I CAN HEAR MUSIC",
    "count": 1
  },
  {
    "artist": "CYNDI LAUPER",
    "title": "TIME AFTER TIME",
    "count": 1
  },
  {
    "artist": "HEINZ RUDOLF KUNZE",
    "title": "MIT LEIB UND SEELE",
    "count": 1
  },
  {
    "artist": "LOREEN",
    "title": "EUPHORIA",
    "count": 1
  },
  {
    "artist": "BILLY IDOL",
    "title": "SWEET SIXTEEN",
    "count": 1
  },
  {
    "artist": "ABBA",
    "title": "DOES YOUR MOTHER KNOW",
    "count": 1
  },
  {
    "artist": "CYNDI LAUPER",
    "title": "GIRLS JUST WANT TO HAVE FUN",
    "count": 1
  },
  {
    "artist": "SIMON &amp; GARFUNKEL",
    "title": "THE BOXER",
    "count": 1
  },
  {
    "artist": "SASHA",
    "title": "COMING HOME",
    "count": 1
  },
  {
    "artist": "KLINGANDE",
    "title": "JUBEL",
    "count": 1
  },
  {
    "artist": "MIDDLE OF THE ROAD",
    "title": "CHIRPY CHIRPY CHEEP CHEEP",
    "count": 1
  },
  {
    "artist": "CREEDENCE CLEARWATER REVIVAL",
    "title": "HEY TONIGHT",
    "count": 1
  },
  {
    "artist": "KEIMZEIT",
    "title": "KLING KLANG",
    "count": 1
  },
  {
    "artist": "MADELEINE PEYROUX",
    "title": "HELLO BABE",
    "count": 1
  },
  {
    "artist": "REAL THING",
    "title": "YOU TO ME ARE EVERYTHING",
    "count": 1
  },
  {
    "artist": "SYDNEY YOUNGBLOOD",
    "title": "IF ONLY I COULD",
    "count": 1
  },
  {
    "artist": "BEATLES",
    "title": "LOVE ME DO",
    "count": 1
  },
  {
    "artist": "LIONS HEAD",
    "title": "WHEN I WAKE UP",
    "count": 1
  },
  {
    "artist": "MADONNA",
    "title": "FROZEN",
    "count": 1
  },
  {
    "artist": "NAMIKA",
    "title": "KOMPLIZIERT",
    "count": 1
  },
  {
    "artist": "ALBERT HAMMOND",
    "title": "THE FREE ELECTRIC BAND",
    "count": 1
  },
  {
    "artist": "MARQUESS",
    "title": "EL TEMPERAMENTO",
    "count": 1
  },
  {
    "artist": "R. KELLY",
    "title": "I BELIEVE I CAN FLY",
    "count": 1
  },
  {
    "artist": "BEE GEES",
    "title": "MASSACHUSETTS",
    "count": 1
  },
  {
    "artist": "OZZY OSBOURNE",
    "title": "DREAMER",
    "count": 1
  },
  {
    "artist": "ROXETTE",
    "title": "SPENDING MY TIME",
    "count": 1
  },
  {
    "artist": "BONNIE TYLER",
    "title": "LOST IN FRANCE",
    "count": 1
  },
  {
    "artist": "SEBASTIAN HAEMER",
    "title": "ALLES NEU",
    "count": 1
  },
  {
    "artist": "BRUNO MARS",
    "title": "GRENADE",
    "count": 1
  },
  {
    "artist": "FREDDIE MERCURY",
    "title": "THE GREAT PRETENDER",
    "count": 1
  },
  {
    "artist": "SARAH CONNOR",
    "title": "WIE SCHOEN DU BIST",
    "count": 1
  },
  {
    "artist": "REAL LIFE",
    "title": "SEND ME AN ANGEL",
    "count": 1
  },
  {
    "artist": "MARIA MCKEE",
    "title": "SHOW ME HEAVEN",
    "count": 1
  },
  {
    "artist": "CLIFF RICHARD",
    "title": "WE DON&#39;T TALK ANYMORE",
    "count": 1
  },
  {
    "artist": "PHILIPP DITTBERNER",
    "title": "IN DEINER KLEINEN WELT",
    "count": 1
  },
  {
    "artist": "OLIVIA NEWTON-JOHN &amp; ELECTRIC LIGHT ORCHESTRA",
    "title": "XANADU",
    "count": 1
  },
  {
    "artist": "SMOKIE",
    "title": "LAY BACK IN THE ARMS OF SOMEONE",
    "count": 1
  },
  {
    "artist": "DIRE STRAITS",
    "title": "SULTANS OF SWING",
    "count": 1
  },
  {
    "artist": "POINTER SISTERS",
    "title": "JUMP (FOR MY LOVE)",
    "count": 1
  },
  {
    "artist": "SHABBY TIGER",
    "title": "SLOW DOWN",
    "count": 2
  },
  {
    "artist": "MARLON ROUDETTE",
    "title": "NEW AGE",
    "count": 1
  },
  {
    "artist": "OLLY FEAT. DEMI LOVATO MURS",
    "title": "UP",
    "count": 1
  },
  {
    "artist": "HARPO",
    "title": "HOROSCOPE",
    "count": 1
  },
  {
    "artist": "ALAN WALKER",
    "title": "FADED",
    "count": 1
  },
  {
    "artist": "ROSE LAURENS",
    "title": "AFRICA",
    "count": 1
  },
  {
    "artist": "LIGHTHOUSE FAMILY",
    "title": "FREE",
    "count": 1
  },
  {
    "artist": "FUN.",
    "title": "WE ARE YOUNG",
    "count": 1
  },
  {
    "artist": "GILBERT O&#39;SULLIVAN",
    "title": "GET DOWN",
    "count": 1
  },
  {
    "artist": "LIMAHL",
    "title": "NEVER ENDING STORY",
    "count": 1
  },
  {
    "artist": "THE STRUMBELLAS",
    "title": "SPIRITS",
    "count": 1
  },
  {
    "artist": "PRINZEN",
    "title": "KUESSEN VERBOTEN",
    "count": 1
  },
  {
    "artist": "AL CORLEY",
    "title": "SQUARE ROOMS",
    "count": 1
  },
  {
    "artist": "BLONDIE",
    "title": "SUNDAY GIRL",
    "count": 1
  },
  {
    "artist": "SILBERMOND",
    "title": "DAS LEICHTESTE DER WELT",
    "count": 1
  },
  {
    "artist": "ERASURE",
    "title": "ALWAYS",
    "count": 1
  },
  {
    "artist": "GEORGE MICHAEL",
    "title": "CARELESS WHISPER",
    "count": 1
  },
  {
    "artist": "R.E.M.",
    "title": "MAN ON THE MOON",
    "count": 1
  },
  {
    "artist": "CORRS",
    "title": "BREATHLESS",
    "count": 1
  },
  {
    "artist": "RONAN KEATING",
    "title": "BABY CAN I HOLD YOU",
    "count": 1
  },
  {
    "artist": "SANTANA",
    "title": "SAMBA PA TI",
    "count": 1
  },
  {
    "artist": "DJ BOBO",
    "title": "AMAZING LIFE",
    "count": 1
  },
  {
    "artist": "INA MUELLER",
    "title": "MARK",
    "count": 1
  },
  {
    "artist": "MADCON FEAT. RAY DALTON",
    "title": "DON&#39;T WORRY",
    "count": 1
  },
  {
    "artist": "PETER GABRIEL",
    "title": "SOLSBURY HILL",
    "count": 1
  },
  {
    "artist": "ORANGE BLUE",
    "title": "SHE&#39;S GOT THAT LIGHT",
    "count": 1
  },
  {
    "artist": "JULI",
    "title": "PERFEKTE WELLE",
    "count": 1
  },
  {
    "artist": "MARQUE",
    "title": "ONE TO MAKE HER HAPPY",
    "count": 1
  },
  {
    "artist": "BARRY WHITE",
    "title": "YOU&#39;RE THE FIRST, THE LAST, MY EVERYTHING",
    "count": 2
  },
  {
    "artist": "SUNRISE AVENUE",
    "title": "LIFESAVER",
    "count": 1
  },
  {
    "artist": "PHARRELL WILLIAMS",
    "title": "HAPPY",
    "count": 1
  },
  {
    "artist": "MICHAEL JACKSON",
    "title": "EARTH SONG",
    "count": 1
  },
  {
    "artist": "LENA",
    "title": "SATELLITE",
    "count": 2
  },
  {
    "artist": "ACE OF BASE",
    "title": "BEAUTIFUL LIFE",
    "count": 1
  },
  {
    "artist": "CHRISTINA STUERMER",
    "title": "EIN TEIL VON MIR",
    "count": 2
  },
  {
    "artist": "LOST FREQUENCIES FEAT. JANIECK DEVY",
    "title": "REALITY",
    "count": 2
  },
  {
    "artist": "ADEL TAWIL",
    "title": "LIEDER",
    "count": 1
  },
  {
    "artist": "AL FEAT. GEORGE DUKE, BONEY JAMES JARREAU",
    "title": "BRING ME JOY",
    "count": 1
  },
  {
    "artist": "SUZI QUATRO",
    "title": "IF YOU CAN&#39;T GIVE ME LOVE",
    "count": 1
  },
  {
    "artist": "ZUCCHERO &amp; PAUL YOUNG",
    "title": "SENZA UNA DONNA",
    "count": 1
  },
  {
    "artist": "CULTURE CLUB",
    "title": "KARMA CHAMELEON",
    "count": 1
  },
  {
    "artist": "MR. MISTER",
    "title": "KYRIE",
    "count": 1
  },
  {
    "artist": "NO DOUBT",
    "title": "DON&#39;T SPEAK",
    "count": 1
  },
  {
    "artist": "ERUPTION",
    "title": "I CAN&#39;T STAND THE RAIN",
    "count": 1
  },
  {
    "artist": "SONNY &amp; CHER",
    "title": "I GOT YOU BABE",
    "count": 1
  },
  {
    "artist": "PETER MAFFAY",
    "title": "ZWEI IN EINEM BOOT",
    "count": 1
  },
  {
    "artist": "HERMAN&#39;S HERMITS",
    "title": "NO MILK TODAY",
    "count": 1
  },
  {
    "artist": "TIM BENDZKO",
    "title": "KEINE MASCHINE",
    "count": 1
  },
  {
    "artist": "MIKE OLDFIELD &amp; MAGGIE REILLY",
    "title": "TO FRANCE",
    "count": 1
  },
  {
    "artist": "RONETTES",
    "title": "BE MY BABY",
    "count": 2
  },
  {
    "artist": "BELL BOOK &amp; CANDLE",
    "title": "RESCUE ME",
    "count": 1
  },
  {
    "artist": "MICHAEL BUBL&Eacute;",
    "title": "I BELIEVE IN YOU",
    "count": 1
  },
  {
    "artist": "STEVIE WONDER",
    "title": "YOU ARE THE SUNSHINE OF MY LIFE",
    "count": 1
  },
  {
    "artist": "DAVID DUNDAS",
    "title": "JEANS ON",
    "count": 1
  },
  {
    "artist": "BILLY SWAN",
    "title": "I CAN HELP",
    "count": 1
  },
  {
    "artist": "DR. HOOK &amp; THE MEDICINE SHOW",
    "title": "SYLVIA&#39;S MOTHER",
    "count": 1
  },
  {
    "artist": "PINK FLOYD",
    "title": "ANOTHER BRICK IN THE WALL",
    "count": 2
  },
  {
    "artist": "XAVIER NAIDOO",
    "title": "BITTE HOER NICHT AUF ZU TRAEUMEN",
    "count": 1
  },
  {
    "artist": "BOSSE",
    "title": "SCHOENSTE ZEIT",
    "count": 2
  },
  {
    "artist": "TINA TURNER",
    "title": "WHAT&#39;S LOVE GOT TO DO WITH IT",
    "count": 1
  },
  {
    "artist": "CROWDED HOUSE",
    "title": "DON&#39;T DREAM IT&#39;S OVER",
    "count": 1
  },
  {
    "artist": "ROXETTE",
    "title": "LISTEN TO YOUR HEART",
    "count": 1
  },
  {
    "artist": "SASHA",
    "title": "I FEEL LONELY",
    "count": 1
  },
  {
    "artist": "SYDNEY YOUNGBLOOD",
    "title": "SIT AND WAIT",
    "count": 1
  },
  {
    "artist": "A-HA",
    "title": "HUNTING HIGH AND LOW",
    "count": 1
  },
  {
    "artist": "FALCO",
    "title": "OUT OF THE DARK",
    "count": 1
  },
  {
    "artist": "DUSTY SPRINGFIELD",
    "title": "IN PRIVATE",
    "count": 1
  },
  {
    "artist": "JAN HAMMER",
    "title": "CROCKETT&#39;S THEME",
    "count": 1
  },
  {
    "artist": "DARIO G",
    "title": "SUNCHYME",
    "count": 1
  },
  {
    "artist": "ELTON JOHN",
    "title": "YOUR SONG",
    "count": 1
  },
  {
    "artist": "PUHDYS",
    "title": "LEBENSZEIT",
    "count": 1
  },
  {
    "artist": "JOHN DENVER",
    "title": "TAKE ME HOME, COUNTRY ROADS",
    "count": 1
  },
  {
    "artist": "KELVIN JONES",
    "title": "CALL YOU HOME",
    "count": 2
  },
  {
    "artist": "INA MUELLER",
    "title": "WENN DU NICHT DA BIST",
    "count": 1
  },
  {
    "artist": "JAMES BLUNT",
    "title": "I&#39;LL BE YOUR MAN",
    "count": 1
  },
  {
    "artist": "SECRET SERVICE",
    "title": "TEN O&#39;CLOCK POSTMAN",
    "count": 2
  },
  {
    "artist": "ARCHIES",
    "title": "SUGAR SUGAR",
    "count": 1
  },
  {
    "artist": "ACE OF BASE",
    "title": "ALL THAT SHE WANTS",
    "count": 1
  },
  {
    "artist": "PATRICK SWAYZE",
    "title": "SHE&#39;S LIKE THE WIND",
    "count": 1
  },
  {
    "artist": "CHRIS NORMAN",
    "title": "MIDNIGHT LADY",
    "count": 1
  },
  {
    "artist": "TRAIN",
    "title": "ANGEL IN BLUE JEANS",
    "count": 1
  },
  {
    "artist": "UDO LINDENBERG",
    "title": "MEIN DING",
    "count": 2
  },
  {
    "artist": "PLATTFOEOET",
    "title": "FRU PUETTELKOW UT HAGENOW",
    "count": 1
  },
  {
    "artist": "ICH + ICH",
    "title": "EINER VON ZWEIEN",
    "count": 1
  },
  {
    "artist": "EMILIA",
    "title": "BIG BIG WORLD",
    "count": 1
  },
  {
    "artist": "EFF",
    "title": "STIMME",
    "count": 2
  },
  {
    "artist": "SCOTT MCKENZIE",
    "title": "SAN FRANCISCO (BE SURE TO WEAR SOME FLOWERS IN YOUR HAIR)",
    "count": 1
  },
  {
    "artist": "SILBERMOND",
    "title": "LEICHTES GEPAECK",
    "count": 1
  },
  {
    "artist": "SPORTFREUNDE STILLER",
    "title": "DAS GESCHENK",
    "count": 1
  },
  {
    "artist": "ICH + ICH",
    "title": "VOM SELBEN STERN",
    "count": 1
  },
  {
    "artist": "COLBIE CAILLAT",
    "title": "I DO",
    "count": 1
  },
  {
    "artist": "SIMPLY RED",
    "title": "IF YOU DON&#39;T KNOW ME BY NOW",
    "count": 1
  },
  {
    "artist": "CAMOUFLAGE",
    "title": "LOVE IS A SHIELD",
    "count": 1
  },
  {
    "artist": "DEE DEE BRIDGEWATER",
    "title": "WATERMELON MAN",
    "count": 1
  },
  {
    "artist": "PUR",
    "title": "FREUNDE",
    "count": 1
  },
  {
    "artist": "TINA TURNER",
    "title": "WHEN THE HEARTACHE IS OVER",
    "count": 1
  },
  {
    "artist": "MANFRED MANN&#39;S EARTH BAND",
    "title": "DAVY&#39;S ON THE ROAD AGAIN",
    "count": 1
  },
  {
    "artist": "ADELE",
    "title": "WHEN WE WERE YOUNG",
    "count": 1
  },
  {
    "artist": "FUN FACTORY",
    "title": "CELEBRATION",
    "count": 1
  },
  {
    "artist": "MONKEES",
    "title": "DAYDREAM BELIEVER",
    "count": 2
  },
  {
    "artist": "CULTURE CLUB",
    "title": "DO YOU REALLY WANT TO HURT ME",
    "count": 1
  },
  {
    "artist": "RIHANNA",
    "title": "DIAMONDS",
    "count": 1
  },
  {
    "artist": "BYRDS",
    "title": "MR. TAMBOURINE MAN",
    "count": 1
  },
  {
    "artist": "ABBA",
    "title": "DANCING QUEEN",
    "count": 1
  },
  {
    "artist": "BOSSHOSS FEAT. THE COMMON LINNETS",
    "title": "JOLENE",
    "count": 1
  },
  {
    "artist": "STRANGLERS",
    "title": "ALWAYS THE SUN",
    "count": 1
  },
  {
    "artist": "THREE DEGREES",
    "title": "WHEN WILL I SEE YOU AGAIN",
    "count": 1
  },
  {
    "artist": "MATTHIAS SCHWEIGH&Ouml;FER",
    "title": "LACHEN WEINEN TANZEN",
    "count": 1
  },
  {
    "artist": "JENNIFER LOPEZ",
    "title": "AIN&#39;T YOUR MAMA",
    "count": 1
  },
  {
    "artist": "ZAGER &amp; EVANS",
    "title": "IN THE YEAR 2525",
    "count": 1
  },
  {
    "artist": "TANITA TIKARAM",
    "title": "WORLD OUTSIDE YOUR WINDOW",
    "count": 1
  },
  {
    "artist": "SUPERTRAMP",
    "title": "BREAKFAST IN AMERICA",
    "count": 1
  },
  {
    "artist": "NIK KERSHAW",
    "title": "THE RIDDLE",
    "count": 1
  },
  {
    "artist": "WESTERNHAGEN",
    "title": "ES GEHT MIR GUT",
    "count": 1
  },
  {
    "artist": "ELECTRIC LIGHT ORCHESTRA",
    "title": "LIVIN&#39; THING",
    "count": 1
  },
  {
    "artist": "HERBERT GROENEMEYER",
    "title": "LAND UNTER",
    "count": 2
  },
  {
    "artist": "SAVAGE GARDEN",
    "title": "TRULY MADLY DEEPLY",
    "count": 1
  },
  {
    "artist": "MIDNIGHT OIL",
    "title": "BEDS ARE BURNING",
    "count": 1
  },
  {
    "artist": "DEPECHE MODE",
    "title": "PRECIOUS",
    "count": 1
  },
  {
    "artist": "DESMOND DEKKER",
    "title": "YOU CAN GET IT IF YOU REALLY WANT",
    "count": 1
  },
  {
    "artist": "PHILIPP DITTBERNER &amp; MARV",
    "title": "WOLKE 4",
    "count": 1
  },
  {
    "artist": "KOOL &amp; THE GANG",
    "title": "FRESH",
    "count": 1
  },
  {
    "artist": "CREEDENCE CLEARWATER REVIVAL",
    "title": "HAVE YOU EVER SEEN THE RAIN ?",
    "count": 1
  },
  {
    "artist": "ENYA",
    "title": "ORINOCO FLOW",
    "count": 1
  },
  {
    "artist": "HOT CHOCOLATE",
    "title": "SO YOU WIN AGAIN",
    "count": 1
  },
  {
    "artist": "JOY FLEMING &amp; JULIANO ROSSI",
    "title": "DU BIST HEUTE WIE NEU",
    "count": 1
  },
  {
    "artist": "NAZARETH",
    "title": "DREAM ON",
    "count": 1
  },
  {
    "artist": "KIM CARNES",
    "title": "BETTE DAVIS EYES",
    "count": 1
  },
  {
    "artist": "MARLON ROUDETTE",
    "title": "ANTI HERO (BRAVE NEW WORLD)",
    "count": 1
  },
  {
    "artist": "MANDO DIAO",
    "title": "DANCE WITH SOMEDOBY",
    "count": 1
  },
  {
    "artist": "JOHN PAUL YOUNG",
    "title": "LOVE IS IN THE AIR",
    "count": 2
  },
  {
    "artist": "QUEEN",
    "title": "A KIND OF MAGIC",
    "count": 1
  },
  {
    "artist": "WHITNEY HOUSTON",
    "title": "ONE MOMENT IN TIME",
    "count": 1
  },
  {
    "artist": "ALVIN STARDUST",
    "title": "I FEEL LIKE BUDDY HOLLY",
    "count": 1
  },
  {
    "artist": "PAUL MCCARTNEY",
    "title": "HOPE OF DELIVERANCE",
    "count": 1
  },
  {
    "artist": "GESTOERT ABER GEIL FEAT. SEBASTIAN HAEMER",
    "title": "ICH &amp; DU",
    "count": 1
  },
  {
    "artist": "SKIFFLE-GRUPPE SCHWERIN",
    "title": "SCHAUSTER UND SNIDER",
    "count": 1
  },
  {
    "artist": "R.E.M.",
    "title": "EVERYBODY HURTS",
    "count": 1
  },
  {
    "artist": "ROBIN BECK",
    "title": "FIRST TIME",
    "count": 1
  },
  {
    "artist": "BRUNO MARS",
    "title": "MARRY YOU",
    "count": 1
  },
  {
    "artist": "ELLIE GOULDING",
    "title": "LOVE ME LIKE YOU DO",
    "count": 2
  },
  {
    "artist": "BARRY MANILOW",
    "title": "MANDY",
    "count": 2
  },
  {
    "artist": "JAMES BLUNT",
    "title": "BONFIRE HEART",
    "count": 1
  },
  {
    "artist": "BILLY OCEAN",
    "title": "SUDDENLY",
    "count": 1
  },
  {
    "artist": "JENNIFER LOPEZ",
    "title": "ON THE FLOOR",
    "count": 1
  },
  {
    "artist": "SIMPLE MINDS",
    "title": "DON&#39;T YOU (FORGET ABOUT ME)",
    "count": 1
  },
  {
    "artist": "ROLLING STONES",
    "title": "(I CAN&#39;T GET NO) SATISFACTION",
    "count": 1
  },
  {
    "artist": "LOONA",
    "title": "HIJO DE LA LUNA",
    "count": 1
  },
  {
    "artist": "WEATHER GIRLS",
    "title": "IT&#39;S RAINING MEN",
    "count": 1
  },
  {
    "artist": "JAMES BAY",
    "title": "HOLD BACK THE RIVER",
    "count": 1
  },
  {
    "artist": "X AMBASSADORS",
    "title": "RENEGADES",
    "count": 1
  },
  {
    "artist": "MARK FORSTER",
    "title": "FLASH MICH",
    "count": 1
  },
  {
    "artist": "EURYTHMICS",
    "title": "MIRACLE OF LOVE",
    "count": 1
  },
  {
    "artist": "SUZI QUATRO",
    "title": "SHE&#39;S IN LOVE WITH YOU",
    "count": 1
  },
  {
    "artist": "MEGHAN TRAINOR",
    "title": "DEAR FUTURE HUSBAND",
    "count": 1
  },
  {
    "artist": "ROBBIE WILLIAMS",
    "title": "ANGELS",
    "count": 1
  },
  {
    "artist": "FLEETWOOD MAC",
    "title": "OH DIANE",
    "count": 1
  },
  {
    "artist": "JIMMY CLIFF",
    "title": "I CAN SEE CLEARLY NOW",
    "count": 1
  },
  {
    "artist": "KIM WILDE",
    "title": "KIDS IN AMERICA",
    "count": 1
  },
  {
    "artist": "THEM",
    "title": "IT&#39;S ALL OVER NOW, BABY BLUE",
    "count": 1
  },
  {
    "artist": "ABBA",
    "title": "WATERLOO",
    "count": 1
  },
  {
    "artist": "SUPREMES",
    "title": "YOU CAN&#39;T HURRY LOVE",
    "count": 1
  },
  {
    "artist": "KWABS",
    "title": "WALK",
    "count": 1
  },
  {
    "artist": "LISA STANSFIELD",
    "title": "ALL AROUND THE WORLD",
    "count": 1
  },
  {
    "artist": "PAUL YOUNG",
    "title": "LOVE OF THE COMMON PEOPLE",
    "count": 1
  },
  {
    "artist": "RONAN KEATING",
    "title": "IF TOMORROW NEVER COMES",
    "count": 1
  },
  {
    "artist": "BEE GEES",
    "title": "STAYIN&#39; ALIVE",
    "count": 1
  },
  {
    "artist": "FAMILY OF THE YEAR",
    "title": "HERO",
    "count": 1
  },
  {
    "artist": "DEPECHE MODE",
    "title": "SHAKE THE DISEASE",
    "count": 1
  },
  {
    "artist": "ECHT",
    "title": "DU TRAEGST KEINE LIEBE IN DIR",
    "count": 1
  },
  {
    "artist": "ERIC PRYDZ",
    "title": "CALL ON ME",
    "count": 1
  },
  {
    "artist": "SHOWADDYWADDY",
    "title": "UNDER THE MOON OF LOVE",
    "count": 1
  },
  {
    "artist": "INA MUELLER",
    "title": "DREI MAENNER HER",
    "count": 1
  },
  {
    "artist": "ICH + ICH",
    "title": "UNIVERSUM",
    "count": 1
  },
  {
    "artist": "LOS BRAVOS",
    "title": "BLACK IS BLACK",
    "count": 1
  },
  {
    "artist": "SIMON &amp; GARFUNKEL",
    "title": "THE SOUND OF SILENCE",
    "count": 2
  },
  {
    "artist": "COLBIE CAILLAT",
    "title": "FALLIN&#39; FOR YOU",
    "count": 1
  },
  {
    "artist": "ICH + ICH",
    "title": "PFLASTER",
    "count": 1
  },
  {
    "artist": "SANDRA",
    "title": "MARIA MAGDALENA",
    "count": 1
  },
  {
    "artist": "VANCE JOY",
    "title": "RIPTIDE",
    "count": 1
  },
  {
    "artist": "ALPHAVILLE",
    "title": "FOREVER YOUNG",
    "count": 1
  },
  {
    "artist": "BOBBY MCFERRIN",
    "title": "DON&#39;T WORRY, BE HAPPY",
    "count": 1
  },
  {
    "artist": "FUGEES",
    "title": "KILLING ME SOFTLY",
    "count": 1
  },
  {
    "artist": "JORIS",
    "title": "HERZ UEBER KOPF",
    "count": 1
  },
  {
    "artist": "EXILE",
    "title": "HOW COULD THIS GO WRONG",
    "count": 1
  },
  {
    "artist": "DAWN",
    "title": "KNOCK THREE TIMES",
    "count": 1
  },
  {
    "artist": "DON HENLEY",
    "title": "THE BOYS OF SUMMER",
    "count": 1
  },
  {
    "artist": "PENNY MCLEAN",
    "title": "1-2-3-4...FIRE!",
    "count": 1
  },
  {
    "artist": "CREEDENCE CLEARWATER REVIVAL",
    "title": "UP AROUND THE BEND",
    "count": 1
  },
  {
    "artist": "ROXETTE",
    "title": "CRASH! BOOM! BANG!",
    "count": 1
  },
  {
    "artist": "MAX GIESINGER",
    "title": "WENN SIE TANZT",
    "count": 4
  },
  {
    "artist": "ABBA",
    "title": "S.O.S.",
    "count": 1
  },
  {
    "artist": "VISAGE",
    "title": "FADE TO GREY",
    "count": 1
  },
  {
    "artist": "SIMPLY RED",
    "title": "HOLDING BACK THE YEARS",
    "count": 1
  },
  {
    "artist": "TOTO",
    "title": "HOLD THE LINE",
    "count": 1
  },
  {
    "artist": "SUPERTRAMP",
    "title": "IT&#39;S RAINING AGAIN",
    "count": 1
  },
  {
    "artist": "OMD",
    "title": "MAID OF ORLEANS",
    "count": 1
  },
  {
    "artist": "A-HA",
    "title": "TAKE ON ME",
    "count": 1
  },
  {
    "artist": "KUNGS FEAT. JAMIE N. COMMONS",
    "title": "DON&#39;T YOU KNOW",
    "count": 2
  },
  {
    "artist": "REA GARVEY",
    "title": "ARMOUR",
    "count": 1
  },
  {
    "artist": "BOY MEETS GIRL",
    "title": "WAITING FOR A STAR TO FALL",
    "count": 1
  },
  {
    "artist": "STANFOUR",
    "title": "HEARTS WITHOUT A HOME",
    "count": 1
  },
  {
    "artist": "HADDAWAY",
    "title": "WHAT IS LOVE",
    "count": 1
  },
  {
    "artist": "PUHDYS",
    "title": "GEH ZU IHR",
    "count": 1
  },
  {
    "artist": "TIM FEAT. CASSANDRA STEEN BENDZKO",
    "title": "UNTER DIE HAUT",
    "count": 1
  },
  {
    "artist": "SOFT CELL",
    "title": "TAINTED LOVE",
    "count": 1
  },
  {
    "artist": "KARAT",
    "title": "SCHWANENKOENIG",
    "count": 1
  },
  {
    "artist": "ROD STEWART",
    "title": "I DON&#39;T WANT TO TALK ABOUT IT",
    "count": 2
  },
  {
    "artist": "LYNYRD SKYNYRD",
    "title": "SWEET HOME ALABAMA",
    "count": 1
  },
  {
    "artist": "JENNIFER RUSH",
    "title": "IF YOU&#39;RE EVER GONNA LOSE MY LOVE",
    "count": 1
  },
  {
    "artist": "ICEHOUSE",
    "title": "HEY LITTLE GIRL",
    "count": 1
  },
  {
    "artist": "JASON DERULO",
    "title": "WANT TO WANT ME",
    "count": 1
  },
  {
    "artist": "ABBA",
    "title": "BANG-A-BOOMERANG",
    "count": 2
  },
  {
    "artist": "JOE COCKER",
    "title": "UNCHAIN MY HEART",
    "count": 1
  },
  {
    "artist": "CHRISTIAN SCOTT",
    "title": "THE RED ROOSTER",
    "count": 1
  },
  {
    "artist": "RINGO STARR",
    "title": "PHOTOGRAPH",
    "count": 1
  },
  {
    "artist": "JOHANNES OERDING",
    "title": "WENN DU LEBST",
    "count": 2
  },
  {
    "artist": "MICHAEL SEMBELLO",
    "title": "MANIAC",
    "count": 1
  },
  {
    "artist": "COMMON LINNETS",
    "title": "CALM AFTER THE STORM",
    "count": 1
  },
  {
    "artist": "HEINZ RUDOLF KUNZE",
    "title": "DEIN IST MEIN GANZES HERZ",
    "count": 1
  },
  {
    "artist": "OLLY MURS",
    "title": "GROW UP",
    "count": 1
  },
  {
    "artist": "VANESSA PARADIS",
    "title": "JOE LE TAXI",
    "count": 1
  },
  {
    "artist": "ANDREAS BOURANI",
    "title": "AUF ANDEREN WEGEN",
    "count": 1
  },
  {
    "artist": "DEN HARROW",
    "title": "DON&#39;T BREAK MY HEART",
    "count": 1
  },
  {
    "artist": "SMOKIE",
    "title": "FOR A FEW DOLLARS MORE",
    "count": 2
  },
  {
    "artist": "FELIX FEAT. JASMINE THOMPSON JAEHN",
    "title": "AIN&#39;T NOBODY (LOVES ME BETTER)",
    "count": 5
  },
  {
    "artist": "URIAH HEEP",
    "title": "LADY IN BLACK",
    "count": 1
  },
  {
    "artist": "PUR",
    "title": "LENA",
    "count": 1
  },
  {
    "artist": "YARED UND DIE SCHLICKRUTSCHER",
    "title": "LAAT MAN LOOPEN",
    "count": 1
  },
  {
    "artist": "HERBERT GROENEMEYER",
    "title": "MAENNER",
    "count": 1
  },
  {
    "artist": "EVELYN THOMAS",
    "title": "HIGH ENERGY",
    "count": 1
  },
  {
    "artist": "FICTION FACTORY",
    "title": "FEELS LIKE HEAVEN",
    "count": 1
  },
  {
    "artist": "SAILOR",
    "title": "THE SECRETARY",
    "count": 1
  },
  {
    "artist": "IMANY",
    "title": "DON&#39;T BE SO SHY",
    "count": 1
  },
  {
    "artist": "MANFRED MANN",
    "title": "MIGHTY QUINN",
    "count": 1
  },
  {
    "artist": "RICK ASTLEY",
    "title": "NEVER GONNA GIVE YOU UP",
    "count": 1
  },
  {
    "artist": "AURA DIONE",
    "title": "SONG FOR SOPHIE",
    "count": 1
  },
  {
    "artist": "RAG&#39;N&#39;BONE MAN",
    "title": "HUMAN",
    "count": 2
  },
  {
    "artist": "REA GARVEY",
    "title": "CAN&#39;T SAY NO",
    "count": 1
  },
  {
    "artist": "CHRIS DE BURGH",
    "title": "SAILING AWAY",
    "count": 1
  },
  {
    "artist": "CHARLIE PUTH",
    "title": "ONE CALL AWAY",
    "count": 2
  },
  {
    "artist": "MOODY BLUES",
    "title": "NIGHTS IN WHITE SATIN",
    "count": 1
  },
  {
    "artist": "PURPLE SCHULZ",
    "title": "DU HAST MIR GERADE NOCH GEFEHLT",
    "count": 1
  },
  {
    "artist": "SWEET",
    "title": "FUNNY, FUNNY",
    "count": 1
  },
  {
    "artist": "CLOUT",
    "title": "SUBSTITUTE",
    "count": 1
  },
  {
    "artist": "SHANIA TWAIN",
    "title": "FOREVER AND FOR ALWAYS",
    "count": 1
  },
  {
    "artist": "OLSEN BROTHERS",
    "title": "FLY ON THE WINGS OF LOVE",
    "count": 1
  },
  {
    "artist": "OWEN PAUL",
    "title": "MY FAVOURITE WASTE OF TIME",
    "count": 1
  },
  {
    "artist": "HALL &amp; OATES",
    "title": "MANEATER",
    "count": 1
  },
  {
    "artist": "GENESIS",
    "title": "FOLLOW YOU, FOLLOW ME",
    "count": 1
  },
  {
    "artist": "MICHAEL JACKSON",
    "title": "BILLIE JEAN",
    "count": 1
  },
  {
    "artist": "REVOLVERHELD",
    "title": "DEINE NAEHE TUT MIR WEH",
    "count": 1
  },
  {
    "artist": "DICK BRAVE &amp; THE BACKBEATS",
    "title": "TAKE GOOD CARE OF MY BABY",
    "count": 1
  },
  {
    "artist": "JAZZ ORANGE",
    "title": "ZZ ORANGE",
    "count": 1
  },
  {
    "artist": "NAMIKA",
    "title": "LIEBLINGSMENSCH",
    "count": 1
  },
  {
    "artist": "LEVINA",
    "title": "PERFECT LIFE",
    "count": 4
  },
  {
    "artist": "THOM PACE",
    "title": "MAYBE",
    "count": 1
  },
  {
    "artist": "CHRISTINA STUERMER",
    "title": "SEITE AN SEITE",
    "count": 3
  },
  {
    "artist": "ANNA FEAT. ALLE FARBEN/YOUNOTUS NAKLAB",
    "title": "SUPERGIRL",
    "count": 1
  },
  {
    "artist": "PETER FOX",
    "title": "HAUS AM SEE",
    "count": 2
  },
  {
    "artist": "EMMELIE DE FOREST",
    "title": "ONLY TEARDROPS",
    "count": 1
  },
  {
    "artist": "ROLLING STONES",
    "title": "MISS YOU",
    "count": 1
  },
  {
    "artist": "ISRAEL &quot;IZ&quot; KAMAKAWIWO&#39;OLE",
    "title": "OVER THE RAINBOW",
    "count": 1
  },
  {
    "artist": "PENNY MCLEAN",
    "title": "LADY BUMP",
    "count": 1
  },
  {
    "artist": "SPORTFREUNDE STILLER",
    "title": "APPLAUS, APPLAUS",
    "count": 1
  },
  {
    "artist": "PE WERNER",
    "title": "KRIBBELN IM BAUCH",
    "count": 1
  },
  {
    "artist": "TROGGS",
    "title": "WILD THING",
    "count": 1
  },
  {
    "artist": "GLENN MILLER &amp; HIS ORCHESTRA",
    "title": "CHATTANOOGA CHOO CHOO",
    "count": 1
  },
  {
    "artist": "PERCY SLEDGE",
    "title": "WHEN A MAN LOVES A WOMAN",
    "count": 1
  },
  {
    "artist": "CHRIS ISAAK",
    "title": "WICKED GAME",
    "count": 1
  },
  {
    "artist": "JAM &amp; SPOON",
    "title": "RIGHT IN THE NIGHT (FALL IN LOVE WITH MUSIC)",
    "count": 1
  },
  {
    "artist": "TIM BENDZKO",
    "title": "LEICHTSINN",
    "count": 2
  },
  {
    "artist": "ANNETT LOUISAN",
    "title": "AUF DICH HAB ICH GEWARTET",
    "count": 1
  },
  {
    "artist": "NENA",
    "title": "WILLST DU MIT MIR GEHN",
    "count": 1
  },
  {
    "artist": "BONNIE TYLER",
    "title": "BITTERBLUE",
    "count": 1
  },
  {
    "artist": "MARK FORSTER",
    "title": "CHOERE",
    "count": 1
  },
  {
    "artist": "TRAIN",
    "title": "HEY, SOUL SISTER",
    "count": 1
  },
  {
    "artist": "PET SHOP BOYS",
    "title": "ALWAYS ON MY MIND",
    "count": 1
  },
  {
    "artist": "CHARLIE FEAT. MEGHAN TRAINOR PUTH",
    "title": "MARVIN GAYE",
    "count": 1
  },
  {
    "artist": "JOHN PARR",
    "title": "ST. ELMO&#39;S FIRE (MAN IN MOTION)",
    "count": 1
  },
  {
    "artist": "ONEREPUBLIC",
    "title": "COUNTING STARS",
    "count": 1
  },
  {
    "artist": "UDO LINDENBERG",
    "title": "DURCH DIE SCHWEREN ZEITEN",
    "count": 2
  },
  {
    "artist": "RACEY",
    "title": "LAY YOUR LOVE ON ME",
    "count": 1
  },
  {
    "artist": "GAZEBO",
    "title": "I LIKE CHOPIN",
    "count": 1
  },
  {
    "artist": "ROBIN SCHULZ &amp; J.U.D.G.E.",
    "title": "SHOW ME LOVE",
    "count": 2
  },
  {
    "artist": "BALTIMORA",
    "title": "TARZAN BOY",
    "count": 1
  },
  {
    "artist": "EAGLES",
    "title": "NEW KID IN TOWN",
    "count": 1
  },
  {
    "artist": "OMD",
    "title": "PANDORA&#39;S BOX",
    "count": 1
  },
  {
    "artist": "MR. BIG",
    "title": "TO BE WITH YOU",
    "count": 1
  },
  {
    "artist": "MANFRED MANN&#39;S EARTH BAND",
    "title": "BLINDED BY THE LIGHT",
    "count": 1
  },
  {
    "artist": "STATUS QUO",
    "title": "WHATEVER YOU WANT",
    "count": 1
  },
  {
    "artist": "ALLE FARBEN",
    "title": "BAD IDEAS",
    "count": 4
  },
  {
    "artist": "CAT STEVENS",
    "title": "MORNING HAS BROKEN",
    "count": 1
  },
  {
    "artist": "CHRIS DE BURGH",
    "title": "SHIP TO SHORE",
    "count": 1
  },
  {
    "artist": "MAX GIESINGER",
    "title": "80 MILLIONEN",
    "count": 3
  },
  {
    "artist": "BERLIN",
    "title": "TAKE MY BREATH AWAY",
    "count": 1
  },
  {
    "artist": "DOORS",
    "title": "LIGHT MY FIRE",
    "count": 1
  },
  {
    "artist": "NANCY SINATRA &amp; FRANK SINATRA",
    "title": "SOMETHIN&#39; STUPID",
    "count": 1
  },
  {
    "artist": "SCRIPT",
    "title": "SUPERHEROES",
    "count": 1
  },
  {
    "artist": "MELANIE C",
    "title": "FIRST DAY OF MY LIFE",
    "count": 1
  },
  {
    "artist": "CAPITAL CITIES",
    "title": "SAFE AND SOUND",
    "count": 1
  },
  {
    "artist": "KERI HILSON",
    "title": "I LIKE",
    "count": 1
  },
  {
    "artist": "EXILE",
    "title": "YOU THRILL ME",
    "count": 1
  },
  {
    "artist": "ALBERT HAMMOND",
    "title": "EVERYTHING I WANT TO DO",
    "count": 1
  },
  {
    "artist": "CARLY SIMON",
    "title": "YOU&#39;RE SO VAIN",
    "count": 1
  },
  {
    "artist": "HOT CHOCOLATE",
    "title": "IT STARTED WITH A KISS",
    "count": 1
  },
  {
    "artist": "GEORGE EZRA",
    "title": "BLAME IT ON ME",
    "count": 1
  },
  {
    "artist": "TALK TALK",
    "title": "IT&#39;S MY LIFE",
    "count": 1
  },
  {
    "artist": "SUPERTRAMP",
    "title": "THE LOGICAL SONG",
    "count": 2
  },
  {
    "artist": "ELTON JOHN",
    "title": "I&#39;M STILL STANDING",
    "count": 1
  },
  {
    "artist": "GOTYE",
    "title": "SOMEBODY THAT I USED TO KNOW",
    "count": 1
  },
  {
    "artist": "CELINE DION",
    "title": "MY HEART WILL GO ON",
    "count": 1
  },
  {
    "artist": "LYNN ANDERSON",
    "title": "ROSE GARDEN",
    "count": 1
  },
  {
    "artist": "EVERLY BROTHERS",
    "title": "WAKE UP LITTLE SUSIE",
    "count": 1
  },
  {
    "artist": "ENRIQUE FEAT. WISIN IGLESIAS",
    "title": "DUELE EL CORAZ&Oacute;N",
    "count": 1
  },
  {
    "artist": "CAMOUFLAGE",
    "title": "THE GREAT COMMANDMENT",
    "count": 1
  },
  {
    "artist": "DAVID GUETTA &amp; KELLY ROWLAND",
    "title": "WHEN LOVE TAKES OVER",
    "count": 1
  },
  {
    "artist": "STEPHANIE",
    "title": "IRRESISTIBLE",
    "count": 1
  },
  {
    "artist": "KARAT",
    "title": "DER BLAUE PLANET",
    "count": 1
  },
  {
    "artist": "ANNETT LOUISAN",
    "title": "DRUECK DIE 1",
    "count": 1
  },
  {
    "artist": "MIKE feat. SHY MARTIN PERRY",
    "title": "OCEAN",
    "count": 3
  },
  {
    "artist": "SMOKIE",
    "title": "NEEDLES AND PINS",
    "count": 1
  },
  {
    "artist": "NILSSON",
    "title": "WITHOUT YOU",
    "count": 1
  },
  {
    "artist": "COCK ROBIN",
    "title": "JUST AROUND THE CORNER",
    "count": 1
  },
  {
    "artist": "DOLLY PARTON",
    "title": "JOLENE",
    "count": 1
  },
  {
    "artist": "SMOKIE",
    "title": "DON&#39;T PLAY YOUR ROCK&#39;N ROLL TO ME",
    "count": 1
  },
  {
    "artist": "LES HUMPHRIES SINGERS",
    "title": "MEXICO",
    "count": 1
  },
  {
    "artist": "ANN LEE",
    "title": "2 TIMES",
    "count": 1
  },
  {
    "artist": "MARC COHN",
    "title": "WALKING IN MEMPHIS",
    "count": 3
  },
  {
    "artist": "VELILE &amp; SAFRI DUO",
    "title": "HELELE",
    "count": 1
  },
  {
    "artist": "QUEEN",
    "title": "RADIO GA GA",
    "count": 1
  },
  {
    "artist": "MADONNA",
    "title": "LIKE A VIRGIN",
    "count": 1
  },
  {
    "artist": "SARAH BRIGHTMAN &amp; ANDREA BOCELLI",
    "title": "TIME TO SAY GOODBYE",
    "count": 1
  },
  {
    "artist": "EURYTHMICS",
    "title": "SWEET DREAMS (ARE MADE OF THIS)",
    "count": 1
  },
  {
    "artist": "TRACY CHAPMAN",
    "title": "BABY CAN I HOLD YOU",
    "count": 1
  },
  {
    "artist": "ELECTRIC LIGHT ORCHESTRA",
    "title": "CONFUSION",
    "count": 1
  },
  {
    "artist": "UNHEILIG",
    "title": "GLUECK AUF DAS LEBEN",
    "count": 1
  },
  {
    "artist": "JUSTIN DJ SNAKE FEAT. BIEBER",
    "title": "LET ME LOVE YOU",
    "count": 4
  },
  {
    "artist": "BEATLES",
    "title": "PENNY LANE",
    "count": 1
  },
  {
    "artist": "ENRIQUE IGLESIAS",
    "title": "THE RHYTHM DIVINE",
    "count": 1
  },
  {
    "artist": "KYGO FEAT. CONRAD",
    "title": "FIRESTONE",
    "count": 1
  },
  {
    "artist": "NEK",
    "title": "LAURA NON C&#39;E",
    "count": 1
  },
  {
    "artist": "BARCLAY JAMES HARVEST",
    "title": "LIFE IS FOR LIVING",
    "count": 1
  },
  {
    "artist": "BELLAMY BROTHERS",
    "title": "SATIN SHEETS",
    "count": 1
  },
  {
    "artist": "FOREIGNER",
    "title": "I WANT TO KNOW WHAT LOVE IS",
    "count": 1
  },
  {
    "artist": "MAMAS &amp; PAPAS",
    "title": "MONDAY, MONDAY",
    "count": 2
  },
  {
    "artist": "MILOW",
    "title": "YOU DON&#39;T KNOW",
    "count": 1
  },
  {
    "artist": "MADONNA",
    "title": "LA ISLA BONITA",
    "count": 1
  },
  {
    "artist": "DEEP BLUE SOMETHING",
    "title": "BREAKFAST AT TIFFANY&#39;S",
    "count": 1
  },
  {
    "artist": "SWEET",
    "title": "WIG WAM BAM",
    "count": 1
  },
  {
    "artist": "SOULTANS",
    "title": "CAN&#39;T TAKE MY HANDS OF YOU",
    "count": 1
  },
  {
    "artist": "TWO OF US",
    "title": "BLUE NIGHT SHADOW",
    "count": 1
  },
  {
    "artist": "CLOUT",
    "title": "SAVE ME",
    "count": 1
  },
  {
    "artist": "JENNIFER RUSH",
    "title": "I COME UNDONE",
    "count": 1
  },
  {
    "artist": "HARPO",
    "title": "MOVIE STAR",
    "count": 1
  },
  {
    "artist": "DEPECHE MODE",
    "title": "JUST CAN&#39;T GET ENOUGH",
    "count": 1
  }
]
